README
setup.py
catalogs/README.sources
catalogs/Update
catalogs/freq.dat
catalogs/freq_RDBE.dat
catalogs/linefreqs.dat
catalogs/locations.dat
catalogs/messages.txt
catalogs/peak.cmd
catalogs/peak_RDBE_DDC.cmd
catalogs/peak_RDBE_PFB.cmd
catalogs/pointing_source_fluxes
catalogs/rfc_2015a_cat.key
catalogs/rfc_2018a_cat.key
catalogs/sources.gsfc
catalogs/sources.gsfc.2015feb
catalogs/sources.gsfc2016
catalogs/sources.pointing
catalogs/sources.pttest
catalogs/sources.rfc
catalogs/sources.vlba.2012jul
catalogs/stations.dat
catalogs/stations_RDBE.dat
catalogs/stations_VLA.dat
catalogs/Master_ATNF/freq_ATNF.dat
catalogs/Master_ATNF/locations.dat_from_ATNF
catalogs/Master_ATNF/locations_ATNF.dat
catalogs/Master_ATNF/stations_ATNF.dat
catalogs/Master_JIVE/freq_EVN.dat
catalogs/Master_JIVE/locations_KVN.dat
catalogs/Master_JIVE/messages_VEX.txt
catalogs/Master_JIVE/stations_EVN.dat
catalogs/Master_JIVE/stations_KVN.dat
catalogs/Master_NRAO/DSN_rationalization.txt
catalogs/Master_NRAO/README
catalogs/Master_NRAO/freq.3mm.krichbaum.2005nov15
catalogs/Master_NRAO/freq_APT.dat
catalogs/Master_NRAO/freq_Arecibo.dat
catalogs/Master_NRAO/freq_DSN.dat
catalogs/Master_NRAO/freq_GB.dat
catalogs/Master_NRAO/freq_RDBE_EB.dat
catalogs/Master_NRAO/freq_RDBE_GB.dat
catalogs/Master_NRAO/freq_RDBE_VLBA.dat
catalogs/Master_NRAO/freq_RDBE_top.dat
catalogs/Master_NRAO/freq_VLA.dat
catalogs/Master_NRAO/freq_VLBA.dat
catalogs/Master_NRAO/freq_geodesy.dat
catalogs/Master_NRAO/freq_mm.dat
catalogs/Master_NRAO/freq_top.dat
catalogs/Master_NRAO/gbt4mmfreqs.dat
catalogs/Master_NRAO/locations.dat.2005f
catalogs/Master_NRAO/locations.dat.2008a
catalogs/Master_NRAO/locations.dat.2009a
catalogs/Master_NRAO/locations.dat.2010a
catalogs/Master_NRAO/locations.dat.gsfc2011a
catalogs/Master_NRAO/locations.dat.gsfc_2014a
catalogs/Master_NRAO/locations.gsfc
catalogs/Master_NRAO/locations.gsfc.2015feb.dat
catalogs/Master_NRAO/locations.top
catalogs/Master_NRAO/locations_DSN.dat
src/pythonSCHED.egg-info/PKG-INFO
src/pythonSCHED.egg-info/SOURCES.txt
src/pythonSCHED.egg-info/dependency_links.txt
src/pythonSCHED.egg-info/requires.txt
src/pythonSCHED.egg-info/top_level.txt