Metadata-Version: 1.2
Name: pythonSCHED
Version: 1.3.0
Summary: Python extension of NRAO's VLBI scheduling program SCHED (see http://www.aoc.nrao.edu/~cwalker/sched/)
Home-page: https://github.com/jive-vlbi/sched
Author: Bob Eldering
Author-email: eldering@jive.eu
License: UNKNOWN
Platform: UNKNOWN
Classifier: Programming Language :: Python :: 3
Classifier: Programming Language :: Fortran
Classifier: Operating System :: POSIX :: Linux
Classifier: Operating System :: MacOS
Classifier: License :: OSI Approved :: GNU General Public License v3 (GPLv3)
Classifier: Intended Audience :: Science/Research
Classifier: Topic :: Scientific/Engineering :: Astronomy
Requires-Python: >=3
